[
     [
          {
               "line": "1",
               "state": "28",
               "token": "a",
               "type": "Id"
          },
          {
               "line": "1",
               "state": "95",
               "token": "=",
               "type": "RELAT(EQUAL)"
          },
          {
               "line": "1",
               "state": -1,
               "token": "5",
               "type": "Number"
          }
     ],
     [
          {
               "line": "2",
               "state": "1",
               "token": "if",
               "type": "Keyword"
          },
          {
               "line": "2",
               "state": -1,
               "token": "a_2",
               "type": "Id"
          },
          {
               "line": "2",
               "state": "94",
               "token": ">",
               "type": "RELAT(GT)"
          },
          {
               "line": "2",
               "state": -1,
               "token": "2",
               "type": "Number"
          },
          {
               "line": "2",
               "state": -1,
               "token": "{",
               "type": "DELIM(LBRACK)"
          }
     ],
     [
          {
               "line": "3",
               "state": "28",
               "token": "a",
               "type": "Id"
          },
          {
               "line": "3",
               "state": "95",
               "token": "=",
               "type": "RELAT(EQUAL)"
          },
          {
               "line": "3",
               "state": "28",
               "token": "a",
               "type": "Id"
          },
          {
               "line": "3",
               "state": "52",
               "token": "-",
               "type": "ARITH(MINUS)"
          },
          {
               "line": "3",
               "state": -1,
               "token": "1",
               "type": "Number"
          }
     ],
     [
          {
               "line": "4",
               "state": -1,
               "token": "}",
               "type": "DELIM(RBRACK)"
          }
     ],
     [
          {
               "line": "5",
               "state": "8",
               "token": "else",
               "type": "Keyword"
          },
          {
               "line": "5",
               "state": -1,
               "token": "{",
               "type": "DELIM(LBRACK)"
          }
     ],
     [
          {
               "line": "6",
               "state": "28",
               "token": "a",
               "type": "Id"
          },
          {
               "line": "6",
               "state": "95",
               "token": "=",
               "type": "RELAT(EQUAL)"
          },
          {
               "line": "6",
               "state": "28",
               "token": "a",
               "type": "Id"
          },
          {
               "line": "6",
               "state": "50",
               "token": "+",
               "type": "ARITH(PLUS)"
          },
          {
               "line": "6",
               "state": -1,
               "token": "1",
               "type": "Number"
          }
     ],
     [
          {
               "line": "7",
               "state": -1,
               "token": "}",
               "type": "DELIM(RBRACK)"
          }
     ],
     [
          {
               "line": "8",
               "state": "17",
               "token": "print",
               "type": "Keyword"
          },
          {
               "line": "8",
               "state": "70",
               "token": "(",
               "type": "DELIM(LPAREN)"
          },
          {
               "line": "8",
               "state": "28",
               "token": "a",
               "type": "Id"
          },
          {
               "line": "8",
               "state": "72",
               "token": ")",
               "type": "DELIM(RPAREN)"
          }
     ],
     [
          {
               "line": "81",
               "state": -1,
               "token": "$",
               "type": "EOF"
          }
     ]
]